odoo/addons/budget_activity_expense/README.rst
odoo/addons/budget_activity_expense/__init__.py
odoo/addons/budget_activity_expense/__manifest__.py
odoo/addons/budget_activity_expense/models/__init__.py
odoo/addons/budget_activity_expense/models/hr_expense.py
odoo/addons/budget_activity_expense/readme/CONTRIBUTORS.md
odoo/addons/budget_activity_expense/readme/DESCRIPTION.md
odoo/addons/budget_activity_expense/readme/USAGE.md
odoo/addons/budget_activity_expense/static/description/icon.png
odoo/addons/budget_activity_expense/static/description/index.html
odoo/addons/budget_activity_expense/tests/__init__.py
odoo/addons/budget_activity_expense/tests/test_budget_activity_expense.py
odoo/addons/budget_activity_expense/views/expense_budget_move.xml
odoo/addons/budget_activity_expense/views/hr_expense_view.xml
odoo_addon_budget_activity_expense-18.0.1.0.0.1.dist-info/METADATA
odoo_addon_budget_activity_expense-18.0.1.0.0.1.dist-info/WHEEL
odoo_addon_budget_activity_expense-18.0.1.0.0.1.dist-info/top_level.txt
odoo_addon_budget_activity_expense-18.0.1.0.0.1.dist-info/RECORD
